tornadoadfsoauth2/__init__.py
tornadoadfsoauth2/auth.py
tornadoadfsoauth2/session.py
tornadoadfsoauth2/verify.py
tornadoadfsoauth2-0.0.3.dist-info/LICENSE
tornadoadfsoauth2-0.0.3.dist-info/METADATA
tornadoadfsoauth2-0.0.3.dist-info/WHEEL
tornadoadfsoauth2-0.0.3.dist-info/top_level.txt
tornadoadfsoauth2-0.0.3.dist-info/RECORD
