Metadata-Version: 2.1
Name: tornadoadfsoauth2
Version: 0.0.3
Summary: ADFS Oauth2 authentication for tornadoweb
Home-page: https://github.com/oh6hay/tornadoadfsoauth2
Author: Ossi Vaananen
Author-email: ossi.vaananen@me.com
License: BSD 3-clause
Platform: UNKNOWN
Requires-Dist: tornadoweb
Requires-Dist: pyjwt
Requires-Dist: cryptography
